polydown/__init__.py
polydown/__main__.py
polydown/api.py
polydown/cli.py
polydown/controller.py
polydown/downloader.py
polydown-0.4.0.dist-info/METADATA
polydown-0.4.0.dist-info/WHEEL
polydown-0.4.0.dist-info/entry_points.txt
polydown-0.4.0.dist-info/licenses/LICENSE
polydown-0.4.0.dist-info/RECORD
