Metadata-Version: 2.4
Name: polydown
Version: 0.4.0
Summary: Batch downloader for polyhaven (polyhaven.com)
Project-URL: Homepage, https://github.com/agmmnn/polydown
Project-URL: Repository, https://github.com/agmmnn/polydown
Project-URL: Changelog, https://github.com/agmmnn/polydown/releases
Project-URL: Bug Tracker, https://github.com/agmmnn/polydown/issues
Author-email: Gökçe Merdun <agmmnn@gmail.com>
License: MIT
License-File: LICENSE
Keywords: batch,download,downloader,hdri,polyhaven,scrape
Classifier: Environment :: Console
Classifier: Operating System :: OS Independent
Classifier: Programming Language :: Python :: 3
Classifier: Topic :: Utilities
Requires-Python: >=3.10
Requires-Dist: aiohttp>=3.13.3
Requires-Dist: requests>=2.32.5
Requires-Dist: rich>=14.2.0
